s3_encryption_sdk/__init__.py
s3_encryption_sdk/bucket.py
s3_encryption_sdk/client.py
s3_encryption_sdk/data_key.py
s3_encryption_sdk/envelope.py
s3_encryption_sdk/object.py
s3_encryption_sdk/wrapping_key.py
s3_encryption_sdk/keys/__init__.py
s3_encryption_sdk/keys/data_key.py
s3_encryption_sdk/keys/wrapping_key.py
s3_encryption_sdk/materials/__init__.py
s3_encryption_sdk/materials/materials.py
s3_encryption_sdk/materials/metadata.py
s3_encryption_sdk/materials_providers/__init__.py
s3_encryption_sdk/materials_providers/base.py
s3_encryption_sdk/materials_providers/context.py
s3_encryption_sdk/materials_providers/kms.py
s3_encryption_sdk/materials_providers/wrapped.py
s3_encryption_sdk-0.0.3.data/data/LICENSE
s3_encryption_sdk-0.0.3.data/data/README.rst
s3_encryption_sdk-0.0.3.dist-info/LICENSE
s3_encryption_sdk-0.0.3.dist-info/METADATA
s3_encryption_sdk-0.0.3.dist-info/WHEEL
s3_encryption_sdk-0.0.3.dist-info/top_level.txt
s3_encryption_sdk-0.0.3.dist-info/RECORD
