Metadata-Version: 2.1
Name: s3-encryption-sdk
Version: 0.0.3
Summary: S3 Encryption Client for Python
Home-page: https://github.com/hupe1980/aws-s3-encryption-python
Author: hupe1980
License: MIT
Keywords: aws s3 kms client-side-encryption
Platform: UNKNOWN
Classifier: Development Status :: 3 - Alpha
Classifier: Intended Audience :: Developers
Classifier: Natural Language :: English
Classifier: License :: OSI Approved :: MIT License
Classifier: Programming Language :: Python
Classifier: Programming Language :: Python :: 3.6
Classifier: Programming Language :: Python :: 3.7
Classifier: Programming Language :: Python :: 3.8
Classifier: Programming Language :: Python :: 3.9
Classifier: Topic :: Security
Classifier: Topic :: Security :: Cryptography
Requires-Python: >= 3.6
Requires-Dist: boto3 (>=1.16.63)
Requires-Dist: cryptography (>=3.3.1)
